[{
  "Author": "Codaaaaaa",
  "Name": "AutoPalExplorer",
  "InternalName": "AutoPalExplorer",
  "AssemblyVersion": "1.0.0.9",
  "Description": "测试用",
  "ApplicableVersion": "any",
  "Tags": [
    "utility",
    "deepdungeon",
    "navigation"
  ],
  "DalamudApiLevel": 13,
  "LoadRequiredState": 0,
  "LoadSync": false,
  "CanUnloadAsync": false,
  "LoadPriority": 0,
  "IconUrl": "https://raw.githubusercontent.com/Codaaaaaa/Pal/main/logo.png",
  "Punchline": "人人没挂开",
  "AcceptsFeedback": true,
  "DownloadLinkInstall": "https://raw.githubusercontent.com/Codaaaaaa/Pal/main/latest.zip",
  "DownloadLinkUpdate":  "https://raw.githubusercontent.com/Codaaaaaa/Pal/main/latest.zip"
}]